{
	"floors": [
		{ "id": "flr_wood", "name": "木地板", "hp": 100, "hardness": 0.4, "flammable": true, "burnTime": 60, "slipFactor": 0.1, "noiseLevel": 0.3, "texture": "wood_floor_01" },
		{ "id": "flr_wood_dark", "name": "深色木地板", "hp": 100, "hardness": 0.4, "flammable": true, "burnTime": 60, "slipFactor": 0.1, "noiseLevel": 0.3, "texture": "wood_floor_dark_01" },
		{ "id": "flr_wood_parquet", "name": "拼花木地板", "hp": 120, "hardness": 0.45, "flammable": true, "burnTime": 70, "slipFactor": 0.1, "noiseLevel": 0.25, "texture": "wood_parquet_01" },
		{ "id": "flr_wood_bamboo", "name": "竹地板", "hp": 80, "hardness": 0.35, "flammable": true, "burnTime": 50, "slipFactor": 0.15, "noiseLevel": 0.2, "texture": "bamboo_floor_01" },
		{ "id": "flr_wood_tatami", "name": "榻榻米", "hp": 50, "hardness": 0.2, "flammable": true, "burnTime": 30, "slipFactor": 0.05, "noiseLevel": 0.1, "comfort": 20, "texture": "tatami_01" },
		{ "id": "flr_concrete", "name": "混凝土地面", "hp": 500, "hardness": 0.9, "flammable": false, "slipFactor": 0.2, "noiseLevel": 0.5, "texture": "concrete_floor_01" },
		{ "id": "flr_concrete_polished", "name": "抛光混凝土", "hp": 500, "hardness": 0.9, "flammable": false, "slipFactor": 0.35, "noiseLevel": 0.4, "texture": "concrete_polished_01" },
		{ "id": "flr_tile_ceramic", "name": "瓷砖地面", "hp": 150, "hardness": 0.7, "flammable": false, "slipFactor": 0.4, "noiseLevel": 0.6, "texture": "tile_ceramic_01" },
		{ "id": "flr_tile_ceramic_white", "name": "白色瓷砖", "hp": 150, "hardness": 0.7, "flammable": false, "slipFactor": 0.4, "noiseLevel": 0.6, "texture": "tile_ceramic_white_01" },
		{ "id": "flr_tile_ceramic_black", "name": "黑色瓷砖", "hp": 150, "hardness": 0.7, "flammable": false, "slipFactor": 0.4, "noiseLevel": 0.6, "texture": "tile_ceramic_black_01" },
		{ "id": "flr_tile_checkered", "name": "棋盘格瓷砖", "hp": 150, "hardness": 0.7, "flammable": false, "slipFactor": 0.4, "noiseLevel": 0.6, "texture": "tile_checkered_01" },
		{ "id": "flr_tile_terracotta", "name": "陶土砖", "hp": 200, "hardness": 0.75, "flammable": false, "slipFactor": 0.25, "noiseLevel": 0.5, "texture": "tile_terracotta_01" },
		{ "id": "flr_marble", "name": "大理石地面", "hp": 300, "hardness": 0.85, "flammable": false, "slipFactor": 0.45, "noiseLevel": 0.7, "texture": "marble_floor_01" },
		{ "id": "flr_marble_white", "name": "白色大理石", "hp": 300, "hardness": 0.85, "flammable": false, "slipFactor": 0.45, "noiseLevel": 0.7, "texture": "marble_white_01" },
		{ "id": "flr_marble_black", "name": "黑色大理石", "hp": 300, "hardness": 0.85, "flammable": false, "slipFactor": 0.45, "noiseLevel": 0.7, "texture": "marble_black_01" },
		{ "id": "flr_granite", "name": "花岗岩地面", "hp": 400, "hardness": 0.9, "flammable": false, "slipFactor": 0.3, "noiseLevel": 0.65, "texture": "granite_floor_01" },
		{ "id": "flr_stone", "name": "石板地面", "hp": 350, "hardness": 0.85, "flammable": false, "slipFactor": 0.25, "noiseLevel": 0.6, "texture": "stone_floor_01" },
		{ "id": "flr_stone_cobble", "name": "鹅卵石地面", "hp": 300, "hardness": 0.8, "flammable": false, "slipFactor": 0.2, "noiseLevel": 0.55, "texture": "cobblestone_01" },
		{ "id": "flr_stone_ancient", "name": "古代石板", "hp": 250, "hardness": 0.75, "flammable": false, "slipFactor": 0.2, "noiseLevel": 0.5, "texture": "stone_ancient_floor_01" },
		{ "id": "flr_brick", "name": "砖地面", "hp": 250, "hardness": 0.8, "flammable": false, "slipFactor": 0.2, "noiseLevel": 0.55, "texture": "brick_floor_01" },
		{ "id": "flr_carpet", "name": "地毯", "hp": 30, "hardness": 0.1, "flammable": true, "burnTime": 20, "slipFactor": 0.05, "noiseLevel": 0.1, "comfort": 15, "texture": "carpet_01" },
		{ "id": "flr_carpet_red", "name": "红色地毯", "hp": 30, "hardness": 0.1, "flammable": true, "burnTime": 20, "slipFactor": 0.05, "noiseLevel": 0.1, "comfort": 15, "texture": "carpet_red_01" },
		{ "id": "flr_carpet_blue", "name": "蓝色地毯", "hp": 30, "hardness": 0.1, "flammable": true, "burnTime": 20, "slipFactor": 0.05, "noiseLevel": 0.1, "comfort": 15, "texture": "carpet_blue_01" },
		{ "id": "flr_carpet_ornate", "name": "华丽地毯", "hp": 30, "hardness": 0.1, "flammable": true, "burnTime": 20, "slipFactor": 0.05, "noiseLevel": 0.1, "comfort": 25, "texture": "carpet_ornate_01" },
		{ "id": "flr_linoleum", "name": "油毡地面", "hp": 50, "hardness": 0.3, "flammable": true, "burnTime": 15, "slipFactor": 0.2, "noiseLevel": 0.2, "texture": "linoleum_01" },
		{ "id": "flr_vinyl", "name": "乙烯基地板", "hp": 60, "hardness": 0.35, "flammable": true, "burnTime": 10, "slipFactor": 0.25, "noiseLevel": 0.15, "texture": "vinyl_floor_01" },
		{ "id": "flr_rubber", "name": "橡胶地面", "hp": 80, "hardness": 0.4, "flammable": true, "burnTime": 25, "slipFactor": 0.1, "noiseLevel": 0.15, "texture": "rubber_floor_01" },
		{ "id": "flr_metal_grate", "name": "金属格栅", "hp": 200, "hardness": 0.8, "flammable": false, "slipFactor": 0.15, "noiseLevel": 0.8, "seeThrough": true, "texture": "metal_grate_01" },
		{ "id": "flr_metal_plate", "name": "金属板地面", "hp": 300, "hardness": 0.85, "flammable": false, "slipFactor": 0.3, "noiseLevel": 0.75, "conductive": true, "texture": "metal_plate_floor_01" },
		{ "id": "flr_metal_diamond", "name": "花纹钢板", "hp": 300, "hardness": 0.85, "flammable": false, "slipFactor": 0.15, "noiseLevel": 0.7, "conductive": true, "texture": "metal_diamond_01" },
		{ "id": "flr_glass", "name": "玻璃地面", "hp": 50, "hardness": 0.6, "flammable": false, "slipFactor": 0.35, "noiseLevel": 0.6, "seeThrough": true, "texture": "glass_floor_01" },
		{ "id": "flr_glass_reinforced", "name": "钢化玻璃地面", "hp": 150, "hardness": 0.75, "flammable": false, "slipFactor": 0.35, "noiseLevel": 0.55, "seeThrough": true, "texture": "glass_reinforced_floor_01" },
		{ "id": "flr_dirt", "name": "泥土地面", "hp": 50, "hardness": 0.2, "flammable": false, "slipFactor": 0.15, "noiseLevel": 0.2, "texture": "dirt_floor_01" },
		{ "id": "flr_sand", "name": "沙地", "hp": 30, "hardness": 0.1, "flammable": false, "slipFactor": 0.25, "noiseLevel": 0.15, "speedPenalty": 0.2, "texture": "sand_floor_01" },
		{ "id": "flr_grass", "name": "草地", "hp": 20, "hardness": 0.1, "flammable": true, "burnTime": 10, "slipFactor": 0.1, "noiseLevel": 0.1, "texture": "grass_floor_01" },
		{ "id": "flr_gravel", "name": "碎石地面", "hp": 100, "hardness": 0.5, "flammable": false, "slipFactor": 0.2, "noiseLevel": 0.6, "texture": "gravel_floor_01" },
		{ "id": "flr_asphalt", "name": "沥青地面", "hp": 200, "hardness": 0.7, "flammable": false, "slipFactor": 0.2, "noiseLevel": 0.4, "texture": "asphalt_01" },
		{ "id": "flr_water_shallow", "name": "浅水", "hp": 9999, "hardness": 0, "flammable": false, "slipFactor": 0.4, "noiseLevel": 0.5, "speedPenalty": 0.3, "wet": true, "texture": "water_shallow_01" },
		{ "id": "flr_ice", "name": "冰面", "hp": 100, "hardness": 0.7, "flammable": false, "slipFactor": 0.95, "noiseLevel": 0.3, "meltable": true, "texture": "ice_floor_01" },
		{ "id": "flr_snow", "name": "雪地", "hp": 20, "hardness": 0.05, "flammable": false, "slipFactor": 0.3, "noiseLevel": 0.1, "speedPenalty": 0.15, "meltable": true, "texture": "snow_floor_01" },
		{ "id": "flr_lava", "name": "岩浆", "hp": 9999, "hardness": 0, "flammable": false, "slipFactor": 0.1, "noiseLevel": 0.2, "contactDamage": 50, "fireDamage": true, "texture": "lava_01", "glowColor": "#ff4400", "glowIntensity": 2.0 },
		{ "id": "flr_magic_circle", "name": "魔法阵", "hp": 200, "hardness": 0.5, "flammable": false, "slipFactor": 0.2, "noiseLevel": 0.3, "magicBonus": 1.2, "texture": "magic_circle_01", "glowColor": "#6644ff", "glowIntensity": 0.5 },
		{ "id": "flr_summoning_circle", "name": "召唤阵", "hp": 200, "hardness": 0.5, "flammable": false, "slipFactor": 0.2, "noiseLevel": 0.3, "summonBonus": 1.5, "texture": "summoning_circle_01", "glowColor": "#ff0066", "glowIntensity": 0.8 },
		{ "id": "flr_rune_circle", "name": "符文阵", "hp": 200, "hardness": 0.5, "flammable": false, "slipFactor": 0.2, "noiseLevel": 0.3, "runeBonus": 1.3, "texture": "rune_circle_01", "glowColor": "#00aaff", "glowIntensity": 0.4 },
		{ "id": "flr_prayer_mat", "name": "祈祷垫", "hp": 30, "hardness": 0.1, "flammable": true, "burnTime": 15, "slipFactor": 0.05, "noiseLevel": 0.05, "prayerBonus": 1.2, "texture": "prayer_mat_01" },
		{ "id": "flr_zen_garden", "name": "枯山水", "hp": 50, "hardness": 0.2, "flammable": false, "slipFactor": 0.15, "noiseLevel": 0.1, "meditationBonus": 1.3, "texture": "zen_garden_01" },
		{ "id": "flr_cyber_panel", "name": "赛博面板", "hp": 150, "hardness": 0.6, "flammable": false, "slipFactor": 0.2, "noiseLevel": 0.3, "powerUse": 1, "texture": "cyber_panel_01", "glowColor": "#00ffff", "glowIntensity": 0.3 },
		{ "id": "flr_neon_grid", "name": "霓虹网格", "hp": 100, "hardness": 0.5, "flammable": false, "slipFactor": 0.25, "noiseLevel": 0.2, "powerUse": 2, "texture": "neon_grid_01", "glowColor": "#ff00ff", "glowIntensity": 0.6 },
		{ "id": "flr_holographic", "name": "全息地板", "hp": 80, "hardness": 0.4, "flammable": false, "slipFactor": 0.2, "noiseLevel": 0.1, "powerUse": 3, "texture": "holographic_floor_01", "glowColor": "#00ff88", "glowIntensity": 0.4 },
		{ "id": "flr_gold", "name": "黄金地面", "hp": 200, "hardness": 0.6, "flammable": false, "slipFactor": 0.35, "noiseLevel": 0.5, "value": 5000, "texture": "gold_floor_01" },
		{ "id": "flr_jade", "name": "玉石地面", "hp": 250, "hardness": 0.7, "flammable": false, "slipFactor": 0.3, "noiseLevel": 0.4, "value": 3000, "texture": "jade_floor_01" },
		{ "id": "flr_obsidian", "name": "黑曜石地面", "hp": 400, "hardness": 0.9, "flammable": false, "slipFactor": 0.35, "noiseLevel": 0.6, "texture": "obsidian_floor_01" },
		{ "id": "flr_crystal", "name": "水晶地面", "hp": 150, "hardness": 0.7, "flammable": false, "slipFactor": 0.4, "noiseLevel": 0.5, "seeThrough": true, "texture": "crystal_floor_01", "glowColor": "#aaddff", "glowIntensity": 0.3 },
		{ "id": "flr_sandstone", "name": "砂岩地面", "hp": 200, "hardness": 0.65, "flammable": false, "slipFactor": 0.2, "noiseLevel": 0.45, "texture": "sandstone_floor_01" },
		{ "id": "flr_hieroglyph", "name": "象形文字地砖", "hp": 200, "hardness": 0.65, "flammable": false, "slipFactor": 0.2, "noiseLevel": 0.45, "texture": "hieroglyph_floor_01" },
		{ "id": "flr_mosaic", "name": "马赛克地面", "hp": 180, "hardness": 0.7, "flammable": false, "slipFactor": 0.35, "noiseLevel": 0.55, "texture": "mosaic_floor_01" },
		{ "id": "flr_greek_pattern", "name": "希腊回纹地面", "hp": 200, "hardness": 0.7, "flammable": false, "slipFactor": 0.3, "noiseLevel": 0.5, "texture": "greek_pattern_01" },
		{ "id": "flr_ship_deck", "name": "船甲板", "hp": 150, "hardness": 0.5, "flammable": true, "burnTime": 80, "slipFactor": 0.2, "noiseLevel": 0.35, "texture": "ship_deck_01" },
		{ "id": "flr_scrap", "name": "废料地面", "hp": 80, "hardness": 0.4, "flammable": false, "slipFactor": 0.25, "noiseLevel": 0.7, "contactDamage": 2, "texture": "scrap_floor_01" },
		{ "id": "flr_rusty_metal", "name": "锈蚀金属", "hp": 150, "hardness": 0.6, "flammable": false, "slipFactor": 0.2, "noiseLevel": 0.65, "texture": "rusty_metal_floor_01" },
		{ "id": "flr_hay", "name": "干草地面", "hp": 20, "hardness": 0.1, "flammable": true, "burnTime": 15, "slipFactor": 0.1, "noiseLevel": 0.15, "texture": "hay_floor_01" },
		{ "id": "flr_flesh", "name": "血肉地面", "hp": 100, "hardness": 0.2, "flammable": true, "burnTime": 30, "slipFactor": 0.5, "noiseLevel": 0.3, "regenerate": true, "regenRate": 2, "texture": "flesh_floor_01" },
		{ "id": "flr_bone", "name": "骨头地面", "hp": 150, "hardness": 0.6, "flammable": false, "slipFactor": 0.2, "noiseLevel": 0.55, "texture": "bone_floor_01" },
		{ "id": "flr_space_station", "name": "空间站地板", "hp": 250, "hardness": 0.8, "flammable": false, "slipFactor": 0.15, "noiseLevel": 0.25, "powerUse": 1, "texture": "space_station_floor_01" },
		{ "id": "flr_forcefield", "name": "力场地板", "hp": 500, "hardness": 1.0, "flammable": false, "slipFactor": 0.1, "noiseLevel": 0.05, "powerUse": 5, "seeThrough": true, "texture": "forcefield_floor_01", "glowColor": "#00aaff", "glowIntensity": 0.8 },
		{ "id": "flr_steam_vent", "name": "蒸汽通风口", "hp": 200, "hardness": 0.7, "flammable": false, "slipFactor": 0.3, "noiseLevel": 0.6, "periodicDamage": 5, "texture": "steam_vent_01" },
		{ "id": "flr_clockwork", "name": "发条地板", "hp": 200, "hardness": 0.75, "flammable": false, "slipFactor": 0.2, "noiseLevel": 0.7, "texture": "clockwork_floor_01" }
	]
}
