{
	"human": {
		"name": "人类",
		"skeleton": "humanoid",
		"examples": ["civilian", "soldier", "merchant", "bandit"],
		"physicsProfile": {
			"mass": "medium",
			"stability": "medium",
			"agility": "medium"
		},
		"defaultAnimations": {
			"idle": "human_idle",
			"walk": "human_walk",
			"run": "human_run",
			"attack": "human_attack_light"
		},
		"combatStyle": "versatile",
		"attackTypes": ["punch", "kick", "weapon_melee", "weapon_ranged"],
		"canUseWeapons": true,
		"canUseItems": true,
		"skillAnimationMapping": {
			"attack_unarmed": "attack_punch",
			"attack_sword": "attack_slash",
			"attack_gun": "attack_shoot",
			"attack_magic": "cast_spell"
		}
	},
	"elf": {
		"name": "精灵",
		"skeleton": "humanoid",
		"examples": ["wood_elf", "high_elf", "dark_elf"],
		"physicsProfile": {
			"mass": "light",
			"stability": "medium",
			"agility": "high"
		},
		"defaultAnimations": {
			"idle": "elf_idle",
			"walk": "elf_walk",
			"run": "elf_run",
			"attack": "elf_attack_light"
		},
		"combatStyle": "finesse",
		"attackTypes": ["bow", "dagger", "magic"],
		"canUseWeapons": true,
		"magicAffinity": "high",
		"skillAnimationMapping": {
			"attack_bow": "attack_bow",
			"attack_dagger": "attack_stab",
			"attack_magic": "cast_spell_graceful"
		}
	},
	"dwarf": {
		"name": "矮人",
		"skeleton": "humanoid",
		"examples": ["miner", "warrior", "smith"],
		"physicsProfile": {
			"mass": "heavy",
			"stability": "very_high",
			"agility": "low"
		},
		"defaultAnimations": {
			"idle": "dwarf_idle",
			"walk": "dwarf_walk",
			"run": "dwarf_run",
			"attack": "dwarf_attack_heavy"
		},
		"combatStyle": "tank",
		"attackTypes": ["axe", "hammer", "shield"],
		"canUseWeapons": true,
		"armorBonus": 1.2,
		"skillAnimationMapping": {
			"attack_axe": "attack_chop",
			"attack_hammer": "attack_smash",
			"attack_shield": "attack_bash"
		}
	},
	"orc": {
		"name": "兽人",
		"skeleton": "humanoid",
		"examples": ["grunt", "berserker", "shaman"],
		"physicsProfile": {
			"mass": "heavy",
			"stability": "high",
			"agility": "medium"
		},
		"defaultAnimations": {
			"idle": "orc_idle",
			"walk": "orc_walk",
			"run": "orc_run",
			"attack": "orc_attack_heavy"
		},
		"combatStyle": "berserker",
		"attackTypes": ["cleave", "smash", "throw", "roar"],
		"canUseWeapons": true,
		"damageBonus": 1.15,
		"skillAnimationMapping": {
			"attack_heavy": "attack_cleave",
			"attack_throw": "attack_throw",
			"attack_special": "attack_roar"
		}
	}
}
